{
    "key": "group_60ca76770a221",
    "title": "Providers - Monitoring",
    "fields": [
        {
            "key": "field_60ca769cfedbd",
            "label": "Short Bio",
            "name": "providers_short_bio",
            "type": "wysiwyg",
            "instructions": "",
            "required": 0,
            "conditional_logic": 0,
            "wrapper": {
                "width": "",
                "class": "",
                "id": ""
            },
            "default_value": "",
            "tabs": "all",
            "toolbar": "basic",
            "media_upload": 1,
            "delay": 0
        },
        {
            "key": "field_60ca76befedbe",
            "label": "What do you do?",
            "name": "what_do_you_do",
            "type": "wysiwyg",
            "instructions": "",
            "required": 0,
            "conditional_logic": 0,
            "wrapper": {
                "width": "",
                "class": "",
                "id": ""
            },
            "default_value": "",
            "tabs": "all",
            "toolbar": "basic",
            "media_upload": 1,
            "delay": 0
        },
        {
            "key": "field_60ca77b9fedbf",
            "label": "How much does it cost?",
            "name": "cost",
            "type": "wysiwyg",
            "instructions": "",
            "required": 0,
            "conditional_logic": 0,
            "wrapper": {
                "width": "",
                "class": "",
                "id": ""
            },
            "default_value": "",
            "tabs": "all",
            "toolbar": "basic",
            "media_upload": 1,
            "delay": 0
        },
        {
            "key": "field_60ca7838fedc0",
            "label": "Video\/Tutorials",
            "name": "video_tutorials",
            "type": "wysiwyg",
            "instructions": "",
            "required": 0,
            "conditional_logic": 0,
            "wrapper": {
                "width": "",
                "class": "",
                "id": ""
            },
            "default_value": "",
            "tabs": "all",
            "toolbar": "basic",
            "media_upload": 1,
            "delay": 0
        },
        {
            "key": "field_60ca797cea343",
            "label": "Sample Use Case",
            "name": "sample_use_case",
            "type": "wysiwyg",
            "instructions": "",
            "required": 0,
            "conditional_logic": 0,
            "wrapper": {
                "width": "",
                "class": "",
                "id": ""
            },
            "default_value": "",
            "tabs": "all",
            "toolbar": "basic",
            "media_upload": 1,
            "delay": 0
        },
        {
            "key": "field_60ca787afedc1",
            "label": "Feature List",
            "name": "feature_list",
            "type": "wysiwyg",
            "instructions": "",
            "required": 0,
            "conditional_logic": 0,
            "wrapper": {
                "width": "",
                "class": "",
                "id": ""
            },
            "default_value": "",
            "tabs": "all",
            "toolbar": "basic",
            "media_upload": 1,
            "delay": 0
        }
    ],
    "location": [
        [
            {
                "param": "post_type",
                "operator": "==",
                "value": "provider"
            },
            {
                "param": "post_taxonomy",
                "operator": "==",
                "value": "provider_category:monitoring"
            }
        ]
    ],
    "menu_order": 0,
    "position": "normal",
    "style": "default",
    "label_placement": "top",
    "instruction_placement": "label",
    "hide_on_screen": "",
    "active": true,
    "description": "",
    "modified": 1623882123
}